yetter/__init__.py
yetter/api.py
yetter/client.py
yetter/types.py
yetter-0.0.3.dist-info/METADATA
yetter-0.0.3.dist-info/WHEEL
yetter-0.0.3.dist-info/top_level.txt
yetter-0.0.3.dist-info/RECORD
