Metadata-Version: 2.4
Name: yetter
Version: 0.0.3
Summary: Yetter Python Client
Author: Yetter <support@yetter.ai>
Project-URL: homepage, https://yetter.ai
Project-URL: repository, https://github.com/SqueezeBits/yetter-client
Requires-Python: >=3.8
Requires-Dist: httpx<1,>=0.21.0
Requires-Dist: httpx-sse<0.5,>=0.4.0
Requires-Dist: pydantic<3.0,>=2.0
